{"573023687930:40@s.whatsapp.net":true,"573126416465@s.whatsapp.net":true,"573126416465:75@s.whatsapp.net":true,"573126416465:76@s.whatsapp.net":true,"573126416465:77@s.whatsapp.net":true,"573204082688@s.whatsapp.net":true,"573218245581@s.whatsapp.net":true,"573218245581:39@s.whatsapp.net":true,"573154726004@s.whatsapp.net":true,"573154726004:54@s.whatsapp.net":true,"573138980308@s.whatsapp.net":true,"573138980308:67@s.whatsapp.net":true,"573146528688@s.whatsapp.net":true,"573146528688:55@s.whatsapp.net":true,"573146528688:57@s.whatsapp.net":true,"573146528688:58@s.whatsapp.net":true,"573118978259@s.whatsapp.net":true,"573127999733@s.whatsapp.net":true,"573133771125@s.whatsapp.net":true,"573133771125:61@s.whatsapp.net":true,"573144906570@s.whatsapp.net":true,"573144906570:3@s.whatsapp.net":true,"573144906570:5@s.whatsapp.net":true,"573117633828@s.whatsapp.net":true,"573124141652@s.whatsapp.net":true,"573219073135@s.whatsapp.net":true,"573006205446@s.whatsapp.net":true,"573125526795@s.whatsapp.net":true,"573125526795:15@s.whatsapp.net":true,"573175028127@s.whatsapp.net":true,"573118085722@s.whatsapp.net":true,"573142557189@s.whatsapp.net":true,"573204138317@s.whatsapp.net":true,"573213342696@s.whatsapp.net":true,"573118401725@s.whatsapp.net":true,"573232311929@s.whatsapp.net":true,"573214190304@s.whatsapp.net":true,"573107602525@s.whatsapp.net":true,"573133956663@s.whatsapp.net":true,"573044131634@s.whatsapp.net":true,"573103118031@s.whatsapp.net":true,"573114402588@s.whatsapp.net":true,"573118178619@s.whatsapp.net":true,"573154221484@s.whatsapp.net":true,"573154221484:28@s.whatsapp.net":true,"573154221484:29@s.whatsapp.net":true,"573143718024@s.whatsapp.net":true,"573143718024:2@s.whatsapp.net":true,"573143718024:3@s.whatsapp.net":true,"573165303173@s.whatsapp.net":true,"573223858314@s.whatsapp.net":true,"573223858314:44@s.whatsapp.net":true,"573212904284@s.whatsapp.net":true,"573209434922@s.whatsapp.net":true,"573205808511@s.whatsapp.net":true,"573134986232@s.whatsapp.net":true,"573208250302@s.whatsapp.net":true,"573208250302:46@s.whatsapp.net":true,"573146725160@s.whatsapp.net":true,"573204883387@s.whatsapp.net":true,"573208476110@s.whatsapp.net":true,"573208476110:24@s.whatsapp.net":true,"573213846359@s.whatsapp.net":true,"573143311227@s.whatsapp.net":true,"573107921659@s.whatsapp.net":true,"573118594130@s.whatsapp.net":true,"573118594130:43@s.whatsapp.net":true,"573012638777@s.whatsapp.net":true,"573108377744@s.whatsapp.net":true,"573156131708@s.whatsapp.net":true,"573222421210@s.whatsapp.net":true,"573222421210:5@s.whatsapp.net":true,"573114636819@s.whatsapp.net":true,"573105688674@s.whatsapp.net":true,"573105688674:40@s.whatsapp.net":true,"573105688674:42@s.whatsapp.net":true,"573223648890@s.whatsapp.net":true,"573202096720@s.whatsapp.net":true,"573209350789@s.whatsapp.net":true,"573208926055@s.whatsapp.net":true,"573107673733@s.whatsapp.net":true,"573115317105@s.whatsapp.net":true,"573114493559@s.whatsapp.net":true,"573114493559:53@s.whatsapp.net":true,"573114493559:56@s.whatsapp.net":true,"573107733938@s.whatsapp.net":true,"573107733938:9@s.whatsapp.net":true,"573212420780@s.whatsapp.net":true,"573132095496@s.whatsapp.net":true,"573132095496:50@s.whatsapp.net":true,"573152129919@s.whatsapp.net":true,"573152129919:80@s.whatsapp.net":true,"573152129919:82@s.whatsapp.net":true,"573152129919:86@s.whatsapp.net":true,"573152129919:87@s.whatsapp.net":true,"573228596706@s.whatsapp.net":true,"573177465886@s.whatsapp.net":true,"573185087730@s.whatsapp.net":true,"573142240244@s.whatsapp.net":true,"573213275187@s.whatsapp.net":true,"573213275187:1@s.whatsapp.net":true,"573214019956@s.whatsapp.net":true,"573208466400@s.whatsapp.net":true,"573102766813@s.whatsapp.net":true,"573204876020@s.whatsapp.net":true,"573195329214@s.whatsapp.net":true,"573195329214:91@s.whatsapp.net":true,"573214620035@s.whatsapp.net":true,"573214620035:55@s.whatsapp.net":true,"573214620035:56@s.whatsapp.net":true,"573207012790@s.whatsapp.net":true,"573188870413@s.whatsapp.net":true,"573174888873@s.whatsapp.net":true,"573223863520@s.whatsapp.net":true,"573102230388@s.whatsapp.net":true,"573138524229@s.whatsapp.net":true,"573116348358@s.whatsapp.net":true,"573222895938@s.whatsapp.net":true,"573227170567@s.whatsapp.net":true,"573204348263@s.whatsapp.net":true,"573143931300@s.whatsapp.net":true,"573158783791@s.whatsapp.net":true,"573185560163@s.whatsapp.net":true,"573219416969@s.whatsapp.net":true,"573229410458@s.whatsapp.net":true,"573136671618@s.whatsapp.net":true,"573157565993@s.whatsapp.net":true,"573132337252@s.whatsapp.net":true,"573122597486@s.whatsapp.net":true,"573122597486:6@s.whatsapp.net":true,"573137690675@s.whatsapp.net":true,"573108853318@s.whatsapp.net":true,"573108853318:62@s.whatsapp.net":true,"573106064433@s.whatsapp.net":true,"573106064433:13@s.whatsapp.net":true,"573144169592@s.whatsapp.net":true,"573154777473@s.whatsapp.net":true,"573156716029@s.whatsapp.net":true,"573125668280@s.whatsapp.net":true,"573209043406@s.whatsapp.net":true,"573209043406:44@s.whatsapp.net":true,"573134319105@s.whatsapp.net":true,"573208443133@s.whatsapp.net":true,"573214629278@s.whatsapp.net":true,"573223350932@s.whatsapp.net":true,"573223350932:5@s.whatsapp.net":true,"573196925332@s.whatsapp.net":true,"573222820732@s.whatsapp.net":true,"573209920931@s.whatsapp.net":true,"573223250150@s.whatsapp.net":true,"573144680701@s.whatsapp.net":true,"573144680701:71@s.whatsapp.net":true,"573144680701:74@s.whatsapp.net":true,"573213096491@s.whatsapp.net":true,"573102494901@s.whatsapp.net":true,"573214058301@s.whatsapp.net":true,"573165148839@s.whatsapp.net":true,"573204093968@s.whatsapp.net":true,"573134211784@s.whatsapp.net":true,"573112246061@s.whatsapp.net":true,"573202749240@s.whatsapp.net":true,"573134703875@s.whatsapp.net":true,"573214873600@s.whatsapp.net":true,"573214873600:27@s.whatsapp.net":true,"573144175972@s.whatsapp.net":true,"573204013358@s.whatsapp.net":true,"573138899111@s.whatsapp.net":true,"573138899111:17@s.whatsapp.net":true,"573142718843@s.whatsapp.net":true,"573124332510@s.whatsapp.net":true,"573124332510:77@s.whatsapp.net":true,"573142059722@s.whatsapp.net":true,"573142059722:35@s.whatsapp.net":true,"573214639211@s.whatsapp.net":true,"573214639211:45@s.whatsapp.net":true,"573144676551@s.whatsapp.net":true,"573117982633@s.whatsapp.net":true,"573203934461@s.whatsapp.net":true,"573142663146@s.whatsapp.net":true,"573219359941@s.whatsapp.net":true,"573228051662@s.whatsapp.net":true,"573138043788@s.whatsapp.net":true,"573136402814@s.whatsapp.net":true,"573223658230@s.whatsapp.net":true,"573173416286@s.whatsapp.net":true,"573161607531@s.whatsapp.net":true,"573202142104@s.whatsapp.net":true,"573209241212@s.whatsapp.net":true,"573107801604@s.whatsapp.net":true,"573107801604:51@s.whatsapp.net":true,"573107801604:55@s.whatsapp.net":true,"573114951930@s.whatsapp.net":true,"573114951930:64@s.whatsapp.net":true,"573138746547@s.whatsapp.net":true,"573118184301@s.whatsapp.net":true,"573162746021@s.whatsapp.net":true,"573212511228@s.whatsapp.net":true,"573158437475@s.whatsapp.net":true,"573158437475:1@s.whatsapp.net":true,"573168216441@s.whatsapp.net":true,"573114626850@s.whatsapp.net":true,"573114626850:68@s.whatsapp.net":true,"573154768749@s.whatsapp.net":true,"573118201181@s.whatsapp.net":true,"573229006126@s.whatsapp.net":true,"573209549811@s.whatsapp.net":true,"573133070835@s.whatsapp.net":true,"573208926877@s.whatsapp.net":true,"573187270855@s.whatsapp.net":true,"573183942734@s.whatsapp.net":true,"573183942734:43@s.whatsapp.net":true,"573175252141@s.whatsapp.net":true,"573162812970@s.whatsapp.net":true,"573148947795@s.whatsapp.net":true,"573125217909@s.whatsapp.net":true,"573174165052@s.whatsapp.net":true,"573133041318@s.whatsapp.net":true,"573133428731@s.whatsapp.net":true,"573112444453@s.whatsapp.net":true,"573212068358@s.whatsapp.net":true,"573118578906@s.whatsapp.net":true,"34624434002@s.whatsapp.net":true,"573162414538@s.whatsapp.net":true,"573213542481@s.whatsapp.net":true,"573203805111@s.whatsapp.net":true,"573214877419@s.whatsapp.net":true,"573153626957@s.whatsapp.net":true,"573184539062@s.whatsapp.net":true,"573044865356@s.whatsapp.net":true,"573118507036@s.whatsapp.net":true,"573228919928@s.whatsapp.net":true,"573228919928:30@s.whatsapp.net":true,"573214028828@s.whatsapp.net":true,"573157672663@s.whatsapp.net":true,"573168092221@s.whatsapp.net":true,"573168092221:5@s.whatsapp.net":true,"573057289202@s.whatsapp.net":true,"573183109172@s.whatsapp.net":true,"573124584056@s.whatsapp.net":true,"573102990920@s.whatsapp.net":true,"573219935852@s.whatsapp.net":true,"573203431442@s.whatsapp.net":true,"573044040993@s.whatsapp.net":true,"573209423861@s.whatsapp.net":true,"34611005204@s.whatsapp.net":true,"573144281268@s.whatsapp.net":true,"573212180597@s.whatsapp.net":true,"573144330845@s.whatsapp.net":true,"573134982427@s.whatsapp.net":true,"573174376546@s.whatsapp.net":true,"573165822148@s.whatsapp.net":true,"573123611907@s.whatsapp.net":true,"573112178020@s.whatsapp.net":true,"573107564487@s.whatsapp.net":true,"573226700280@s.whatsapp.net":true,"573226700280:27@s.whatsapp.net":true,"573213867506@s.whatsapp.net":true,"573138615636@s.whatsapp.net":true,"573108166681@s.whatsapp.net":true,"573227358769@s.whatsapp.net":true,"573132008610@s.whatsapp.net":true,"573132008610:5@s.whatsapp.net":true,"573123756457@s.whatsapp.net":true,"573204241590@s.whatsapp.net":true,"573012401856@s.whatsapp.net":true,"573012401856:25@s.whatsapp.net":true,"573143955519@s.whatsapp.net":true,"573143955519:1@s.whatsapp.net":true,"573143955519:93@s.whatsapp.net":true,"573187818814@s.whatsapp.net":true,"573138798073@s.whatsapp.net":true,"573116196595@s.whatsapp.net":true,"573116196595:42@s.whatsapp.net":true,"573219936616@s.whatsapp.net":true,"573114120261@s.whatsapp.net":true,"573213830579@s.whatsapp.net":true,"573223998046@s.whatsapp.net":true,"573138792644@s.whatsapp.net":true,"573107672088@s.whatsapp.net":true,"573152573331@s.whatsapp.net":true,"573208167177@s.whatsapp.net":true,"573203936099@s.whatsapp.net":true,"573112501012@s.whatsapp.net":true,"573138560703@s.whatsapp.net":true,"573138560703:2@s.whatsapp.net":true,"573143158744@s.whatsapp.net":true,"573102737151@s.whatsapp.net":true,"573209108196@s.whatsapp.net":true,"573124513091@s.whatsapp.net":true,"573124513091:59@s.whatsapp.net":true,"573203594085@s.whatsapp.net":true,"573203594085:1@s.whatsapp.net":true,"573118174147@s.whatsapp.net":true,"573108159188@s.whatsapp.net":true,"573123554226@s.whatsapp.net":true,"573181761839@s.whatsapp.net":true,"573184047783@s.whatsapp.net":true,"573133777424@s.whatsapp.net":true,"573232397605@s.whatsapp.net":true,"573125913413@s.whatsapp.net":true,"573132084193@s.whatsapp.net":true,"573202968525@s.whatsapp.net":true,"573223168560@s.whatsapp.net":true,"573232415081@s.whatsapp.net":true,"573202717748@s.whatsapp.net":true,"573124914015@s.whatsapp.net":true,"573186095747@s.whatsapp.net":true,"573186095747:18@s.whatsapp.net":true,"573186095747:19@s.whatsapp.net":true,"573214993893@s.whatsapp.net":true,"573167450258@s.whatsapp.net":true,"573125845904@s.whatsapp.net":true,"573209464359@s.whatsapp.net":true,"573142287942@s.whatsapp.net":true,"573144642079@s.whatsapp.net":true,"573142490872@s.whatsapp.net":true,"573138959406@s.whatsapp.net":true,"573213992055@s.whatsapp.net":true,"573235203841@s.whatsapp.net":true,"573235203841:84@s.whatsapp.net":true,"573235771215@s.whatsapp.net":true,"573125547874@s.whatsapp.net":true,"573219166617@s.whatsapp.net":true,"573219166617:81@s.whatsapp.net":true,"573219166617:86@s.whatsapp.net":true,"573219166617:87@s.whatsapp.net":true,"573115986852@s.whatsapp.net":true,"573204901583@s.whatsapp.net":true,"573169290944@s.whatsapp.net":true,"573207667903@s.whatsapp.net":true,"573216890186@s.whatsapp.net":true,"573117603766@s.whatsapp.net":true,"573203531458@s.whatsapp.net":true,"573176737417@s.whatsapp.net":true,"573229462031@s.whatsapp.net":true,"573187541453@s.whatsapp.net":true,"573147396337@s.whatsapp.net":true,"573142029576@s.whatsapp.net":true,"573212211553@s.whatsapp.net":true,"573212211553:60@s.whatsapp.net":true,"573146121653@s.whatsapp.net":true,"573138618401@s.whatsapp.net":true,"573223462609@s.whatsapp.net":true,"573102688132@s.whatsapp.net":true,"573137159664@s.whatsapp.net":true,"573132425238@s.whatsapp.net":true,"573132425238:55@s.whatsapp.net":true,"573132425238:56@s.whatsapp.net":true,"573118766658@s.whatsapp.net":true,"573228621064@s.whatsapp.net":true,"573125762724@s.whatsapp.net":true,"573125762724:7@s.whatsapp.net":true,"573124964055@s.whatsapp.net":true,"573144194826@s.whatsapp.net":true,"971501334964@s.whatsapp.net":true,"573504537965@s.whatsapp.net":true,"573133008758@s.whatsapp.net":true,"573144811873@s.whatsapp.net":true,"573116745824@s.whatsapp.net":true,"573228529832@s.whatsapp.net":true,"573228529832:17@s.whatsapp.net":true,"573124381962@s.whatsapp.net":true,"573132782689@s.whatsapp.net":true,"573113801363@s.whatsapp.net":true,"573113801363:33@s.whatsapp.net":true,"573234856593@s.whatsapp.net":true,"573235466310@s.whatsapp.net":true,"573223880706@s.whatsapp.net":true,"573214805092@s.whatsapp.net":true,"573138100241@s.whatsapp.net":true,"573138366213@s.whatsapp.net":true,"573233006973@s.whatsapp.net":true,"573227531925@s.whatsapp.net":true,"573212779690@s.whatsapp.net":true,"573144641795@s.whatsapp.net":true,"573105587418@s.whatsapp.net":true,"573105587418:10@s.whatsapp.net":true,"16614294171@s.whatsapp.net":true,"16614294171:20@s.whatsapp.net":true,"573172325922@s.whatsapp.net":true,"573178417785@s.whatsapp.net":true,"573114695003@s.whatsapp.net":true,"573223850575@s.whatsapp.net":true,"573144043801@s.whatsapp.net":true,"573144043801:40@s.whatsapp.net":true,"573144043801:42@s.whatsapp.net":true,"573506376490@s.whatsapp.net":true,"573214664641@s.whatsapp.net":true,"573133043815@s.whatsapp.net":true,"573175626941@s.whatsapp.net":true,"573123029342@s.whatsapp.net":true,"573144360675@s.whatsapp.net":true,"573152649837@s.whatsapp.net":true,"573117668446@s.whatsapp.net":true,"573208775537@s.whatsapp.net":true,"573155225256@s.whatsapp.net":true,"573155225256:7@s.whatsapp.net":true,"573155225256:8@s.whatsapp.net":true,"573155225256:9@s.whatsapp.net":true,"573155225256:10@s.whatsapp.net":true,"573219955038@s.whatsapp.net":true,"573115187297@s.whatsapp.net":true,"573108697792@s.whatsapp.net":true,"573143415040@s.whatsapp.net":true,"573143415040:39@s.whatsapp.net":true,"573158330112@s.whatsapp.net":true,"573169991704@s.whatsapp.net":true,"573158347773@s.whatsapp.net":true,"573209643649@s.whatsapp.net":true,"573112031447@s.whatsapp.net":true,"573232099092@s.whatsapp.net":true,"573232099092:8@s.whatsapp.net":true,"573209100350@s.whatsapp.net":true,"573124711417@s.whatsapp.net":true,"573170120476@s.whatsapp.net":true,"573229151467@s.whatsapp.net":true,"573506290511@s.whatsapp.net":true,"573222069723@s.whatsapp.net":true,"573176860875@s.whatsapp.net":true,"573118400960@s.whatsapp.net":true,"573118400960:1@s.whatsapp.net":true,"573144114518@s.whatsapp.net":true,"573105455023@s.whatsapp.net":true,"573105455023:6@s.whatsapp.net":true,"573134513220@s.whatsapp.net":true,"573123812581@s.whatsapp.net":true,"573144195439@s.whatsapp.net":true,"573208630390@s.whatsapp.net":true,"573208630390:8@s.whatsapp.net":true,"573208630390:9@s.whatsapp.net":true,"573208630390:10@s.whatsapp.net":true,"573123424492@s.whatsapp.net":true,"573226401387@s.whatsapp.net":true,"573160554895@s.whatsapp.net":true,"573160554895:25@s.whatsapp.net":true,"573143226576@s.whatsapp.net":true,"573228497922@s.whatsapp.net":true,"573223065370@s.whatsapp.net":true,"573144579470@s.whatsapp.net":true,"573124617618@s.whatsapp.net":true,"573156500161@s.whatsapp.net":true,"573188159097@s.whatsapp.net":true,"573162663081@s.whatsapp.net":true,"573162663081:41@s.whatsapp.net":true,"573118129201@s.whatsapp.net":true,"573223834904@s.whatsapp.net":true,"573102552316@s.whatsapp.net":true,"573144398367@s.whatsapp.net":true,"573102964236@s.whatsapp.net":true,"573204312588@s.whatsapp.net":true,"573204312588:4@s.whatsapp.net":true,"573157250275@s.whatsapp.net":true,"573216096021@s.whatsapp.net":true,"573202709326@s.whatsapp.net":true,"573132335969@s.whatsapp.net":true,"573132335969:15@s.whatsapp.net":true,"573115697659@s.whatsapp.net":true,"573115697659:29@s.whatsapp.net":true,"573115697659:30@s.whatsapp.net":true,"573218257737@s.whatsapp.net":true,"573132573457@s.whatsapp.net":true,"573227674932@s.whatsapp.net":true,"573045281644@s.whatsapp.net":true,"573115566490@s.whatsapp.net":true,"573204855864@s.whatsapp.net":true,"573142678695@s.whatsapp.net":true,"573242275528@s.whatsapp.net":true,"573227112888@s.whatsapp.net":true,"573164889097@s.whatsapp.net":true,"573133434860@s.whatsapp.net":true,"573222488930@s.whatsapp.net":true,"573209416248@s.whatsapp.net":true,"573105622187@s.whatsapp.net":true,"573102645430@s.whatsapp.net":true,"573112140929@s.whatsapp.net":true,"573143582930@s.whatsapp.net":true,"573143582930:55@s.whatsapp.net":true,"573143582930:57@s.whatsapp.net":true,"573219745718@s.whatsapp.net":true,"573115271637@s.whatsapp.net":true,"573214873628@s.whatsapp.net":true,"573214873628:55@s.whatsapp.net":true,"573107505934@s.whatsapp.net":true,"573214034639@s.whatsapp.net":true,"573104852617@s.whatsapp.net":true,"573178505494@s.whatsapp.net":true,"573178505494:25@s.whatsapp.net":true,"573227608892@s.whatsapp.net":true,"573227608892:97@s.whatsapp.net":true,"573212854744@s.whatsapp.net":true,"573172458008@s.whatsapp.net":true,"573208512668@s.whatsapp.net":true,"573208314939@s.whatsapp.net":true,"573209834090@s.whatsapp.net":true,"573204002385@s.whatsapp.net":true,"573159261261@s.whatsapp.net":true,"573112345319@s.whatsapp.net":true,"573227623056@s.whatsapp.net":true,"573112229790@s.whatsapp.net":true,"573112229790:84@s.whatsapp.net":true,"573184439608@s.whatsapp.net":true,"573184439608:3@s.whatsapp.net":true,"573184439608:95@s.whatsapp.net":true,"573209461853@s.whatsapp.net":true,"573103144654@s.whatsapp.net":true,"573202691553@s.whatsapp.net":true,"573115236479@s.whatsapp.net":true,"573133024349@s.whatsapp.net":true,"573213867148@s.whatsapp.net":true,"573213867148:1@s.whatsapp.net":true,"573023610668@s.whatsapp.net":true,"573227154343@s.whatsapp.net":true,"573184911389@s.whatsapp.net":true,"573124022927@s.whatsapp.net":true,"573165802387@s.whatsapp.net":true,"573165802387:26@s.whatsapp.net":true,"573143626510@s.whatsapp.net":true,"573202180822@s.whatsapp.net":true,"573202180822:26@s.whatsapp.net":true,"573123704462@s.whatsapp.net":true,"573123704462:24@s.whatsapp.net":true,"573132236823@s.whatsapp.net":true,"573115475060@s.whatsapp.net":true,"573134654669@s.whatsapp.net":true,"573134818633@s.whatsapp.net":true,"573115964066@s.whatsapp.net":true,"573104398434@s.whatsapp.net":true,"573104398434:87@s.whatsapp.net":true,"573123155246@s.whatsapp.net":true,"573123960720@s.whatsapp.net":true,"573123960720:83@s.whatsapp.net":true,"573123960720:84@s.whatsapp.net":true,"573123960720:85@s.whatsapp.net":true,"573227889649@s.whatsapp.net":true,"573222858658@s.whatsapp.net":true,"573222858658:49@s.whatsapp.net":true,"573222858658:51@s.whatsapp.net":true,"573103279720@s.whatsapp.net":true,"573107509591@s.whatsapp.net":true,"573212329041@s.whatsapp.net":true,"573204054621@s.whatsapp.net":true,"573212496540@s.whatsapp.net":true,"573214887901@s.whatsapp.net":true,"573224182990@s.whatsapp.net":true,"573162211349@s.whatsapp.net":true,"573162211349:31@s.whatsapp.net":true,"573180757932@s.whatsapp.net":true,"573223186099@s.whatsapp.net":true,"573223186099:34@s.whatsapp.net":true,"573144678281@s.whatsapp.net":true,"573223187520@s.whatsapp.net":true,"573124647793@s.whatsapp.net":true,"573142490120@s.whatsapp.net":true,"573118737380@s.whatsapp.net":true,"573235342961@s.whatsapp.net":true,"573235342961:72@s.whatsapp.net":true,"573235342961:74@s.whatsapp.net":true,"573107720598@s.whatsapp.net":true,"573102904541@s.whatsapp.net":true,"573144172001@s.whatsapp.net":true,"573175703911@s.whatsapp.net":true,"573227595218@s.whatsapp.net":true,"573213739418@s.whatsapp.net":true,"573144140402@s.whatsapp.net":true,"573156241158@s.whatsapp.net":true,"573156241158:22@s.whatsapp.net":true,"573212860737@s.whatsapp.net":true,"573212860737:51@s.whatsapp.net":true,"573204936212@s.whatsapp.net":true,"573184813444@s.whatsapp.net":true,"573184813444:41@s.whatsapp.net":true,"573003985232@s.whatsapp.net":true,"573157147620@s.whatsapp.net":true,"573152465436@s.whatsapp.net":true,"573022778489@s.whatsapp.net":true,"573022778489:5@s.whatsapp.net":true,"573123699424@s.whatsapp.net":true,"573204715457@s.whatsapp.net":true,"573212829815@s.whatsapp.net":true,"573222931761@s.whatsapp.net":true,"573222931761:39@s.whatsapp.net":true,"573123939934@s.whatsapp.net":true,"573204047433@s.whatsapp.net":true,"573188046731@s.whatsapp.net":true,"573212602883@s.whatsapp.net":true,"573209629692@s.whatsapp.net":true,"573118778613@s.whatsapp.net":true,"573209296505@s.whatsapp.net":true,"573209296505:53@s.whatsapp.net":true,"573134309671@s.whatsapp.net":true,"573152983420@s.whatsapp.net":true,"573152566121@s.whatsapp.net":true,"573152566121:11@s.whatsapp.net":true,"573114452615@s.whatsapp.net":true,"573114452615:30@s.whatsapp.net":true,"573114452615:33@s.whatsapp.net":true,"573182398098@s.whatsapp.net":true,"573208613305@s.whatsapp.net":true,"573118336608@s.whatsapp.net":true,"573204694251@s.whatsapp.net":true,"573118628931@s.whatsapp.net":true,"573118306993@s.whatsapp.net":true,"573118306993:44@s.whatsapp.net":true,"573118306993:48@s.whatsapp.net":true,"573118306993:49@s.whatsapp.net":true,"573158661979@s.whatsapp.net":true,"573232374850@s.whatsapp.net":true,"573177925740@s.whatsapp.net":true,"573177925740:70@s.whatsapp.net":true,"573177925740:91@s.whatsapp.net":true,"573177925740:93@s.whatsapp.net":true,"573103206322@s.whatsapp.net":true,"573102888843@s.whatsapp.net":true,"573223396569@s.whatsapp.net":true,"573156815657@s.whatsapp.net":true,"573156815657:30@s.whatsapp.net":true,"573156815657:31@s.whatsapp.net":true,"573103452402@s.whatsapp.net":true,"573175411249@s.whatsapp.net":true,"573175411249:86@s.whatsapp.net":true,"573175411249:96@s.whatsapp.net":true,"573228473719@s.whatsapp.net":true,"573166147955@s.whatsapp.net":true,"573166147955:95@s.whatsapp.net":true,"573027188096@s.whatsapp.net":true,"573127948909@s.whatsapp.net":true,"573028587830@s.whatsapp.net":true,"573115123578@s.whatsapp.net":true,"573132783513@s.whatsapp.net":true,"573132783513:39@s.whatsapp.net":true,"573208367977@s.whatsapp.net":true,"573142565377@s.whatsapp.net":true,"573112774865@s.whatsapp.net":true,"573168001810@s.whatsapp.net":true,"573207383781@s.whatsapp.net":true,"573164708689@s.whatsapp.net":true,"573164708689:9@s.whatsapp.net":true,"573042154336@s.whatsapp.net":true,"573224164306@s.whatsapp.net":true,"573232410154@s.whatsapp.net":true,"573213160842@s.whatsapp.net":true,"573115205876@s.whatsapp.net":true,"573214949944@s.whatsapp.net":true,"573214949944:44@s.whatsapp.net":true,"573112129436@s.whatsapp.net":true,"573157163830@s.whatsapp.net":true,"573243686350@s.whatsapp.net":true,"573114852696@s.whatsapp.net":true,"573144016197@s.whatsapp.net":true,"573102704837@s.whatsapp.net":true,"573175778628@s.whatsapp.net":true,"573114894236@s.whatsapp.net":true,"573112169874@s.whatsapp.net":true,"573112169874:12@s.whatsapp.net":true,"573112169874:13@s.whatsapp.net":true,"573203309285@s.whatsapp.net":true,"573203309285:38@s.whatsapp.net":true,"573203309285:42@s.whatsapp.net":true,"573203309285:43@s.whatsapp.net":true,"573223775743@s.whatsapp.net":true,"573123564878@s.whatsapp.net":true,"573209053209@s.whatsapp.net":true,"573232505457@s.whatsapp.net":true,"573209463178@s.whatsapp.net":true,"573133920476@s.whatsapp.net":true,"573167312423@s.whatsapp.net":true,"573105712964@s.whatsapp.net":true,"573006743576@s.whatsapp.net":true,"573142607482@s.whatsapp.net":true,"573134211426@s.whatsapp.net":true,"573134211426:45@s.whatsapp.net":true,"573134211426:46@s.whatsapp.net":true,"573124608915@s.whatsapp.net":true,"573144700698@s.whatsapp.net":true,"573105736267@s.whatsapp.net":true,"573105736267:22@s.whatsapp.net":true,"573209618149@s.whatsapp.net":true,"573025689312@s.whatsapp.net":true,"573025689312:57@s.whatsapp.net":true,"573114922951@s.whatsapp.net":true,"573232039313@s.whatsapp.net":true,"573232039313:33@s.whatsapp.net":true,"573115001414@s.whatsapp.net":true,"573204172152@s.whatsapp.net":true,"573227034118@s.whatsapp.net":true,"573134069986@s.whatsapp.net":true,"573132782196@s.whatsapp.net":true,"573180676076@s.whatsapp.net":true,"573213068023@s.whatsapp.net":true,"573214970445@s.whatsapp.net":true,"573105828154@s.whatsapp.net":true,"573204801257@s.whatsapp.net":true,"573214998867@s.whatsapp.net":true,"573214998867:98@s.whatsapp.net":true,"573209122860@s.whatsapp.net":true,"573156776486@s.whatsapp.net":true,"573187478499@s.whatsapp.net":true,"573187478499:11@s.whatsapp.net":true,"573137373736@s.whatsapp.net":true,"573137373736:2@s.whatsapp.net":true,"573102288688@s.whatsapp.net":true,"573107140914@s.whatsapp.net":true,"573126522895@s.whatsapp.net":true,"573143117770@s.whatsapp.net":true,"573184533781@s.whatsapp.net":true,"573228472391@s.whatsapp.net":true,"573208955470@s.whatsapp.net":true,"573112185073@s.whatsapp.net":true,"573112185073:64@s.whatsapp.net":true,"573112185073:65@s.whatsapp.net":true,"573204838348@s.whatsapp.net":true,"573105821702@s.whatsapp.net":true,"573105821702:64@s.whatsapp.net":true,"573104868536@s.whatsapp.net":true,"573102044242@s.whatsapp.net":true,"573122236748@s.whatsapp.net":true,"573152868107@s.whatsapp.net":true,"573186982585@s.whatsapp.net":true,"573132616299@s.whatsapp.net":true,"573132616299:37@s.whatsapp.net":true,"573132616299:38@s.whatsapp.net":true,"573132616299:39@s.whatsapp.net":true,"573152996417@s.whatsapp.net":true,"573115199944@s.whatsapp.net":true,"573115199944:25@s.whatsapp.net":true,"573208243018@s.whatsapp.net":true,"573202492786@s.whatsapp.net":true,"573202492786:66@s.whatsapp.net":true,"573115122983@s.whatsapp.net":true,"573236173010@s.whatsapp.net":true,"573228569831@s.whatsapp.net":true,"573158566394@s.whatsapp.net":true,"573114784755@s.whatsapp.net":true,"573114784755:74@s.whatsapp.net":true,"573138810033@s.whatsapp.net":true,"573026441556@s.whatsapp.net":true,"573143604056@s.whatsapp.net":true,"573168072416@s.whatsapp.net":true,"573168072416:77@s.whatsapp.net":true,"573208067095@s.whatsapp.net":true,"573142883855@s.whatsapp.net":true,"573138191520@s.whatsapp.net":true,"573138191520:25@s.whatsapp.net":true,"573134323979@s.whatsapp.net":true,"573134934123@s.whatsapp.net":true,"573186476328@s.whatsapp.net":true,"573186476328:7@s.whatsapp.net":true,"573144452173@s.whatsapp.net":true,"573152350237@s.whatsapp.net":true,"573209043643@s.whatsapp.net":true,"573118468268@s.whatsapp.net":true,"573222917666@s.whatsapp.net":true,"573104888946@s.whatsapp.net":true,"573178745127@s.whatsapp.net":true,"573178745127:25@s.whatsapp.net":true,"573162839604@s.whatsapp.net":true,"573135472150@s.whatsapp.net":true,"573135472150:9@s.whatsapp.net":true,"573115396768@s.whatsapp.net":true,"573123186336@s.whatsapp.net":true,"573132912295@s.whatsapp.net":true,"573054180841@s.whatsapp.net":true,"573232329114@s.whatsapp.net":true,"573214740039@s.whatsapp.net":true,"573125540382@s.whatsapp.net":true,"573219765410@s.whatsapp.net":true,"573181380206@s.whatsapp.net":true,"573228419791@s.whatsapp.net":true,"573506291372@s.whatsapp.net":true,"573126103378@s.whatsapp.net":true,"573132393030@s.whatsapp.net":true,"573142702894@s.whatsapp.net":true,"573124050036@s.whatsapp.net":true,"573214215911@s.whatsapp.net":true,"573184896958@s.whatsapp.net":true,"573157991122@s.whatsapp.net":true,"573157991122:43@s.whatsapp.net":true,"573170207417@s.whatsapp.net":true,"573226708830@s.whatsapp.net":true,"573218697963@s.whatsapp.net":true,"573124536268@s.whatsapp.net":true,"573208581864@s.whatsapp.net":true,"573168868172@s.whatsapp.net":true,"573162989450@s.whatsapp.net":true,"573123606177@s.whatsapp.net":true,"573107827465@s.whatsapp.net":true,"573155196751@s.whatsapp.net":true,"573138800380@s.whatsapp.net":true,"573133526388@s.whatsapp.net":true,"573133526388:26@s.whatsapp.net":true,"573107577878@s.whatsapp.net":true,"573214343123@s.whatsapp.net":true,"573214343123:37@s.whatsapp.net":true,"573222275177@s.whatsapp.net":true,"573222275177:34@s.whatsapp.net":true,"573222275177:37@s.whatsapp.net":true,"573142899269@s.whatsapp.net":true,"573142899269:34@s.whatsapp.net":true,"573142899269:37@s.whatsapp.net":true,"573208778968@s.whatsapp.net":true,"573208552901@s.whatsapp.net":true,"573223788645@s.whatsapp.net":true,"573227732381@s.whatsapp.net":true,"573157627562@s.whatsapp.net":true,"573142778867@s.whatsapp.net":true,"573144845437@s.whatsapp.net":true,"573003543274@s.whatsapp.net":true,"573214591095@s.whatsapp.net":true,"573214591095:2@s.whatsapp.net":true,"573508482082@s.whatsapp.net":true,"573508482082:33@s.whatsapp.net":true,"573232866654@s.whatsapp.net":true,"573208695395@s.whatsapp.net":true,"573169371696@s.whatsapp.net":true,"573209631025@s.whatsapp.net":true,"573224106488@s.whatsapp.net":true,"573165021126@s.whatsapp.net":true,"573124470371@s.whatsapp.net":true,"573125665466@s.whatsapp.net":true,"573166579738@s.whatsapp.net":true,"573133051659@s.whatsapp.net":true,"573227691397@s.whatsapp.net":true,"573133115326@s.whatsapp.net":true,"573223664823@s.whatsapp.net":true,"573058571900@s.whatsapp.net":true,"573108892221@s.whatsapp.net":true,"573181380209@s.whatsapp.net":true,"573228585191@s.whatsapp.net":true,"573223860787@s.whatsapp.net":true,"573245942500@s.whatsapp.net":true,"573142657577@s.whatsapp.net":true,"573133543243@s.whatsapp.net":true,"573112349448@s.whatsapp.net":true,"573112349448:35@s.whatsapp.net":true,"573107720576@s.whatsapp.net":true,"573174709660@s.whatsapp.net":true,"573125611389@s.whatsapp.net":true,"573202680231@s.whatsapp.net":true,"573202680231:70@s.whatsapp.net":true,"573224801132@s.whatsapp.net":true,"573132685229@s.whatsapp.net":true,"573158667754@s.whatsapp.net":true,"573204564917@s.whatsapp.net":true,"573204564917:17@s.whatsapp.net":true,"573223641095@s.whatsapp.net":true,"573166412588@s.whatsapp.net":true,"573146504347@s.whatsapp.net":true,"573146504347:42@s.whatsapp.net":true,"573207647389@s.whatsapp.net":true,"573207647389:43@s.whatsapp.net":true,"573025187087@s.whatsapp.net":true,"573025187087:10@s.whatsapp.net":true,"573107620624@s.whatsapp.net":true,"573107620624:22@s.whatsapp.net":true,"573107620624:23@s.whatsapp.net":true,"573183720741@s.whatsapp.net":true,"573105503433@s.whatsapp.net":true,"573212650027@s.whatsapp.net":true,"573105533462@s.whatsapp.net":true,"573504203391@s.whatsapp.net":true,"573124451562@s.whatsapp.net":true,"573186806601@s.whatsapp.net":true,"573142404085@s.whatsapp.net":true,"573103012337@s.whatsapp.net":true,"573103012337:65@s.whatsapp.net":true,"573125625063@s.whatsapp.net":true,"573228333534@s.whatsapp.net":true,"573134495484@s.whatsapp.net":true,"573228894293@s.whatsapp.net":true,"573142086297@s.whatsapp.net":true,"573004902783@s.whatsapp.net":true,"573004902783:71@s.whatsapp.net":true,"573222924161@s.whatsapp.net":true,"573134661696@s.whatsapp.net":true,"573124593903@s.whatsapp.net":true,"573214906319@s.whatsapp.net":true,"573503277442@s.whatsapp.net":true,"573147030106@s.whatsapp.net":true,"34611709276@s.whatsapp.net":true,"573143373658@s.whatsapp.net":true,"573143373658:44@s.whatsapp.net":true,"573205803431@s.whatsapp.net":true,"573205803431:14@s.whatsapp.net":true,"573209771100@s.whatsapp.net":true,"573144384340@s.whatsapp.net":true,"573128080086@s.whatsapp.net":true,"573219918142@s.whatsapp.net":true,"573219918142:29@s.whatsapp.net":true,"573123566401@s.whatsapp.net":true,"573144629891@s.whatsapp.net":true,"573219843861@s.whatsapp.net":true,"573233584654@s.whatsapp.net":true,"573202148043@s.whatsapp.net":true,"573143297283@s.whatsapp.net":true,"573143297283:2@s.whatsapp.net":true,"573142471580@s.whatsapp.net":true,"573144740926@s.whatsapp.net":true,"573145857343@s.whatsapp.net":true,"573227634889@s.whatsapp.net":true,"573114573352@s.whatsapp.net":true,"573114247761@s.whatsapp.net":true,"573182215016@s.whatsapp.net":true,"573124472777@s.whatsapp.net":true,"573185464977@s.whatsapp.net":true,"573185464977:87@s.whatsapp.net":true,"573185464977:88@s.whatsapp.net":true,"573212001371@s.whatsapp.net":true,"573125385098@s.whatsapp.net":true,"573208833276@s.whatsapp.net":true,"573104836204@s.whatsapp.net":true,"573103405299@s.whatsapp.net":true,"573112171261@s.whatsapp.net":true,"573209214608@s.whatsapp.net":true,"573112657151@s.whatsapp.net":true,"573112657151:21@s.whatsapp.net":true,"573172256693@s.whatsapp.net":true,"573172256693:23@s.whatsapp.net":true,"573172256693:24@s.whatsapp.net":true,"573103097027@s.whatsapp.net":true,"573103097027:22@s.whatsapp.net":true,"573103097027:25@s.whatsapp.net":true,"573202792788@s.whatsapp.net":true,"573138511186@s.whatsapp.net":true,"573128879289@s.whatsapp.net":true,"573125337677@s.whatsapp.net":true,"573219853360@s.whatsapp.net":true,"573192269261@s.whatsapp.net":true,"573142323368@s.whatsapp.net":true,"573228851817@s.whatsapp.net":true,"573214686040@s.whatsapp.net":true,"573114415272@s.whatsapp.net":true,"573105373906@s.whatsapp.net":true,"573125966007@s.whatsapp.net":true,"573144195206@s.whatsapp.net":true,"573213502691@s.whatsapp.net":true,"573208622107@s.whatsapp.net":true,"573112225813@s.whatsapp.net":true,"573222903485@s.whatsapp.net":true,"573153854833@s.whatsapp.net":true,"573132808917@s.whatsapp.net":true,"573124129961@s.whatsapp.net":true,"573124129961:33@s.whatsapp.net":true,"573213324400@s.whatsapp.net":true,"573219347425@s.whatsapp.net":true,"573152166064@s.whatsapp.net":true,"573166208541@s.whatsapp.net":true,"573115312187@s.whatsapp.net":true,"573138909254@s.whatsapp.net":true,"573124640620@s.whatsapp.net":true,"573144641781@s.whatsapp.net":true,"573135486227@s.whatsapp.net":true,"573124414637@s.whatsapp.net":true,"573223511282@s.whatsapp.net":true,"573218890530@s.whatsapp.net":true,"573192584556@s.whatsapp.net":true,"573115205074@s.whatsapp.net":true,"573132189986@s.whatsapp.net":true,"573229117610@s.whatsapp.net":true,"573229117610:22@s.whatsapp.net":true,"573229117610:25@s.whatsapp.net":true,"573137842591@s.whatsapp.net":true,"573137842591:77@s.whatsapp.net":true,"573137842591:83@s.whatsapp.net":true,"573204500832@s.whatsapp.net":true,"573118051970@s.whatsapp.net":true,"573118051970:6@s.whatsapp.net":true,"573204867697@s.whatsapp.net":true,"573102857846@s.whatsapp.net":true,"573165429138@s.whatsapp.net":true,"573138624009@s.whatsapp.net":true,"573195134153@s.whatsapp.net":true,"573223828636@s.whatsapp.net":true,"573153780253@s.whatsapp.net":true,"573228151135@s.whatsapp.net":true,"573228483779@s.whatsapp.net":true,"573112892670@s.whatsapp.net":true,"573118505590@s.whatsapp.net":true,"573227651498@s.whatsapp.net":true,"573212553388@s.whatsapp.net":true,"573186489987@s.whatsapp.net":true,"573125400936@s.whatsapp.net":true,"573105656165@s.whatsapp.net":true,"573213725578@s.whatsapp.net":true,"573213880249@s.whatsapp.net":true,"573125088747@s.whatsapp.net":true,"573125088747:68@s.whatsapp.net":true,"573144302720@s.whatsapp.net":true,"573207053030@s.whatsapp.net":true,"573208459114@s.whatsapp.net":true,"573223680639@s.whatsapp.net":true,"573235347951@s.whatsapp.net":true,"573102723869@s.whatsapp.net":true,"573133759535@s.whatsapp.net":true,"573203590194@s.whatsapp.net":true,"573204862775@s.whatsapp.net":true,"573133276655@s.whatsapp.net":true,"573133276655:33@s.whatsapp.net":true,"573123120278@s.whatsapp.net":true,"573103290382@s.whatsapp.net":true,"573103290382:31@s.whatsapp.net":true,"573204173954@s.whatsapp.net":true,"573213985258@s.whatsapp.net":true,"573213985258:51@s.whatsapp.net":true,"573142792548@s.whatsapp.net":true,"573504364350@s.whatsapp.net":true,"573134268074@s.whatsapp.net":true,"573212095771@s.whatsapp.net":true,"573168752138@s.whatsapp.net":true,"573137946727@s.whatsapp.net":true,"573102738285@s.whatsapp.net":true,"573015532176@s.whatsapp.net":true,"573214015325@s.whatsapp.net":true,"573217517857@s.whatsapp.net":true,"573134208553@s.whatsapp.net":true,"573134208553:18@s.whatsapp.net":true,"573007435788@s.whatsapp.net":true,"573205571244@s.whatsapp.net":true,"573165004312@s.whatsapp.net":true,"573222851751@s.whatsapp.net":true,"573222851751:1@s.whatsapp.net":true,"573222851751:4@s.whatsapp.net":true,"573118968263@s.whatsapp.net":true,"573157808068@s.whatsapp.net":true,"573214018681@s.whatsapp.net":true,"573123225686@s.whatsapp.net":true,"573134343029@s.whatsapp.net":true,"573134343029:39@s.whatsapp.net":true,"573134343029:43@s.whatsapp.net":true,"573108728564@s.whatsapp.net":true,"573208839381@s.whatsapp.net":true,"573115368778@s.whatsapp.net":true,"573134385094@s.whatsapp.net":true,"573103716829@s.whatsapp.net":true,"573228361600@s.whatsapp.net":true,"573184278954@s.whatsapp.net":true,"573132542396@s.whatsapp.net":true,"573133828535@s.whatsapp.net":true,"573148416424@s.whatsapp.net":true,"573209768526@s.whatsapp.net":true,"573142453313@s.whatsapp.net":true,"573002587215@s.whatsapp.net":true,"573219464048@s.whatsapp.net":true,"573164363737@s.whatsapp.net":true,"573164363737:71@s.whatsapp.net":true,"573164363737:72@s.whatsapp.net":true,"573205581640@s.whatsapp.net":true,"573143536535@s.whatsapp.net":true,"573228527363@s.whatsapp.net":true,"573114607013@s.whatsapp.net":true,"573114607013:11@s.whatsapp.net":true,"573114607013:16@s.whatsapp.net":true,"573114607013:17@s.whatsapp.net":true,"573146798109@s.whatsapp.net":true,"573146798109:43@s.whatsapp.net":true,"573103106393@s.whatsapp.net":true,"573102922280@s.whatsapp.net":true,"573203540880@s.whatsapp.net":true,"573203540880:97@s.whatsapp.net":true,"573142758293@s.whatsapp.net":true,"573142758293:12@s.whatsapp.net":true,"573142758293:15@s.whatsapp.net":true,"573142758293:17@s.whatsapp.net":true,"573122972085@s.whatsapp.net":true,"573102221387@s.whatsapp.net":true,"573106952237@s.whatsapp.net":true,"573223785096@s.whatsapp.net":true,"573204394571@s.whatsapp.net":true,"573168400085@s.whatsapp.net":true,"573112698543@s.whatsapp.net":true,"573164311660@s.whatsapp.net":true,"573204083332@s.whatsapp.net":true,"573214902201@s.whatsapp.net":true,"573043978047@s.whatsapp.net":true,"573125706024@s.whatsapp.net":true,"573124328844@s.whatsapp.net":true,"573222294215@s.whatsapp.net":true,"573133252064@s.whatsapp.net":true,"573241089448@s.whatsapp.net":true,"573223795051@s.whatsapp.net":true,"573113506706@s.whatsapp.net":true,"573222823203@s.whatsapp.net":true,"573134371533@s.whatsapp.net":true,"573228599662@s.whatsapp.net":true,"573132964512@s.whatsapp.net":true,"573222826147@s.whatsapp.net":true,"573132768670@s.whatsapp.net":true,"573223531519@s.whatsapp.net":true,"573177815092@s.whatsapp.net":true,"573177815092:13@s.whatsapp.net":true,"573202360540@s.whatsapp.net":true,"573178921623@s.whatsapp.net":true,"573178921623:20@s.whatsapp.net":true,"573117044869@s.whatsapp.net":true,"573132357101@s.whatsapp.net":true,"573106797442@s.whatsapp.net":true,"573142753180@s.whatsapp.net":true,"573127751273@s.whatsapp.net":true,"573134367769@s.whatsapp.net":true,"573133397131@s.whatsapp.net":true,"573054464817@s.whatsapp.net":true,"573145324739@s.whatsapp.net":true,"573123473344@s.whatsapp.net":true,"573115246667@s.whatsapp.net":true,"573223824406@s.whatsapp.net":true,"573214007358@s.whatsapp.net":true,"573134263812@s.whatsapp.net":true,"573218078937@s.whatsapp.net":true,"573218078937:1@s.whatsapp.net":true,"573218078937:98@s.whatsapp.net":true,"573235203085@s.whatsapp.net":true,"573204900338@s.whatsapp.net":true,"573053178092@s.whatsapp.net":true,"573053178092:67@s.whatsapp.net":true,"33610183611@s.whatsapp.net":true,"573204239610@s.whatsapp.net":true,"573187921115@s.whatsapp.net":true,"573112241582@s.whatsapp.net":true,"573204188668@s.whatsapp.net":true,"573165301725@s.whatsapp.net":true,"573165301725:73@s.whatsapp.net":true,"573165301725:77@s.whatsapp.net":true,"573165301725:78@s.whatsapp.net":true,"573102147546@s.whatsapp.net":true,"573102147546:21@s.whatsapp.net":true,"573102147546:22@s.whatsapp.net":true,"573209396798@s.whatsapp.net":true,"573209183781@s.whatsapp.net":true,"573202518296@s.whatsapp.net":true,"573138001804@s.whatsapp.net":true,"573143300661@s.whatsapp.net":true,"573143300661:4@s.whatsapp.net":true,"573123479568@s.whatsapp.net":true,"573183632750@s.whatsapp.net":true,"573115059850@s.whatsapp.net":true,"573197232354@s.whatsapp.net":true,"573155342793@s.whatsapp.net":true,"573143648344@s.whatsapp.net":true,"573143276134@s.whatsapp.net":true,"573116001951@s.whatsapp.net":true,"573215124495@s.whatsapp.net":true,"573214019911@s.whatsapp.net":true,"573107383349@s.whatsapp.net":true,"573107383349:83@s.whatsapp.net":true,"573148451445@s.whatsapp.net":true,"573148451445:16@s.whatsapp.net":true,"573203834845@s.whatsapp.net":true,"573103720299@s.whatsapp.net":true,"573112443987@s.whatsapp.net":true,"573184132759@s.whatsapp.net":true,"573184132759:76@s.whatsapp.net":true,"573146154303@s.whatsapp.net":true,"573146368557@s.whatsapp.net":true,"573133960921@s.whatsapp.net":true,"573144218003@s.whatsapp.net":true,"573232227034@s.whatsapp.net":true,"573122572313@s.whatsapp.net":true,"573203513009@s.whatsapp.net":true,"573216873315@s.whatsapp.net":true,"573167283499@s.whatsapp.net":true,"573213284109@s.whatsapp.net":true,"573115460392@s.whatsapp.net":true,"573202379587@s.whatsapp.net":true,"573132450720@s.whatsapp.net":true,"573123609896@s.whatsapp.net":true,"573115749202@s.whatsapp.net":true,"573004322024@s.whatsapp.net":true,"573163033532@s.whatsapp.net":true,"573162477031@s.whatsapp.net":true,"573223247649@s.whatsapp.net":true,"573126657767@s.whatsapp.net":true,"573203766835@s.whatsapp.net":true,"573224441869@s.whatsapp.net":true,"573132384845@s.whatsapp.net":true,"573105552522@s.whatsapp.net":true,"573123486961@s.whatsapp.net":true,"573229085007@s.whatsapp.net":true,"573202405567@s.whatsapp.net":true,"573142310550@s.whatsapp.net":true,"573143195861@s.whatsapp.net":true,"573204188116@s.whatsapp.net":true,"573507234393@s.whatsapp.net":true,"573114791352@s.whatsapp.net":true,"573144641807@s.whatsapp.net":true,"573144641807:15@s.whatsapp.net":true,"573203398039@s.whatsapp.net":true,"573203398039:31@s.whatsapp.net":true,"573102154346@s.whatsapp.net":true,"573502867149@s.whatsapp.net":true,"573209031377@s.whatsapp.net":true,"573156095686@s.whatsapp.net":true,"573105731024@s.whatsapp.net":true,"573219612120@s.whatsapp.net":true,"573132239089@s.whatsapp.net":true,"573207135247@s.whatsapp.net":true,"573207135247:1@s.whatsapp.net":true,"573202116571@s.whatsapp.net":true,"573202116571:40@s.whatsapp.net":true,"573202116571:41@s.whatsapp.net":true,"573213035934@s.whatsapp.net":true,"573222306260@s.whatsapp.net":true,"573125039168@s.whatsapp.net":true,"573112792976@s.whatsapp.net":true,"573223627710@s.whatsapp.net":true,"573132067880@s.whatsapp.net":true,"573125793300@s.whatsapp.net":true,"573123949489@s.whatsapp.net":true,"573123949489:8@s.whatsapp.net":true,"573123949489:9@s.whatsapp.net":true,"573144643706@s.whatsapp.net":true,"573209668684@s.whatsapp.net":true,"573209668684:4@s.whatsapp.net":true,"573206979987@s.whatsapp.net":true,"573206979987:57@s.whatsapp.net":true,"573138440144@s.whatsapp.net":true,"573203233500@s.whatsapp.net":true,"573128990787@s.whatsapp.net":true,"573128990787:31@s.whatsapp.net":true,"573124636528@s.whatsapp.net":true,"573134690198@s.whatsapp.net":true,"573108154853@s.whatsapp.net":true,"573108154853:90@s.whatsapp.net":true,"573108154853:93@s.whatsapp.net":true,"573102778630@s.whatsapp.net":true,"573102778630:3@s.whatsapp.net":true,"573144809410@s.whatsapp.net":true,"573118610322@s.whatsapp.net":true,"573132421042@s.whatsapp.net":true,"573164452737@s.whatsapp.net":true,"573214017812@s.whatsapp.net":true,"573178121089@s.whatsapp.net":true,"573138062902@s.whatsapp.net":true,"573138062902:89@s.whatsapp.net":true,"573138062902:90@s.whatsapp.net":true,"573212546435@s.whatsapp.net":true,"573102690043@s.whatsapp.net":true,"573154091336@s.whatsapp.net":true,"573157366681@s.whatsapp.net":true,"573212380867@s.whatsapp.net":true,"573212380867:3@s.whatsapp.net":true,"573212380867:4@s.whatsapp.net":true,"573228139235@s.whatsapp.net":true,"573228139235:61@s.whatsapp.net":true,"573228139235:62@s.whatsapp.net":true,"573228139235:63@s.whatsapp.net":true,"573228139235:64@s.whatsapp.net":true,"573212299640@s.whatsapp.net":true,"573214606639@s.whatsapp.net":true,"573144067527@s.whatsapp.net":true,"573152359794@s.whatsapp.net":true,"573043596960@s.whatsapp.net":true,"573043596960:75@s.whatsapp.net":true,"573008332855@s.whatsapp.net":true,"573132763635@s.whatsapp.net":true,"573133251984@s.whatsapp.net":true,"573133251984:6@s.whatsapp.net":true,"573133251984:7@s.whatsapp.net":true,"573133251984:9@s.whatsapp.net":true,"573132689051@s.whatsapp.net":true,"573157299931@s.whatsapp.net":true,"573015784541@s.whatsapp.net":true,"573112117030@s.whatsapp.net":true,"17032972710@s.whatsapp.net":true,"17032972710:33@s.whatsapp.net":true,"573132060777@s.whatsapp.net":true,"573212503939@s.whatsapp.net":true,"573043014296@s.whatsapp.net":true,"573144705581@s.whatsapp.net":true,"573013260404@s.whatsapp.net":true,"573123903642@s.whatsapp.net":true,"573133230377@s.whatsapp.net":true,"573203799411@s.whatsapp.net":true,"573203799411:70@s.whatsapp.net":true,"573203799411:73@s.whatsapp.net":true,"573027128062@s.whatsapp.net":true,"573115704320@s.whatsapp.net":true,"573115704320:10@s.whatsapp.net":true,"573115704320:11@s.whatsapp.net":true,"573115704320:12@s.whatsapp.net":true,"573115704320:13@s.whatsapp.net":true,"573163611256@s.whatsapp.net":true,"573163611256:37@s.whatsapp.net":true,"573133754671@s.whatsapp.net":true,"573232408079@s.whatsapp.net":true,"573227010253@s.whatsapp.net":true,"573212741134@s.whatsapp.net":true,"573187475562@s.whatsapp.net":true,"573187475562:21@s.whatsapp.net":true,"573023687930@s.whatsapp.net":true}